.gitignore
.readthedocs.yaml
CODE_OF_CONDUCT.md
LICENSE.txt
MANIFEST.in
README.rst
pyproject.toml
setup.py
.github/dependabot.yml
.github/workflows/citest.yml
docs/conf.py
docs/ecl.html
docs/epar.png
docs/index.rst
docs/ipython_notes.txt
docs/prow.png
docs/pyraf_tutorial.rst
docs/teal_guide.rst
docs/_static/brand.css
docs/_static/pyraflogo.png
pyraf/GkiMpl.py
pyraf/MplCanvasAdapter.py
pyraf/Ptkplot.py
pyraf/__init__.py
pyraf/__main__.py
pyraf/aqutil.py
pyraf/blankcursor.xbm
pyraf/cgeneric.py
pyraf/cl2py.py
pyraf/clast.py
pyraf/clcache.py
pyraf/cllinecache.py
pyraf/clparse.py
pyraf/clscan.py
pyraf/cltoken.py
pyraf/epar.optionDB
pyraf/epar.py
pyraf/filecache.py
pyraf/fill_clcache.py
pyraf/fontdata.py
pyraf/generic.py
pyraf/gki.py
pyraf/gkicmd.py
pyraf/gkigcur.py
pyraf/gkiiraf.py
pyraf/gkitkbase.py
pyraf/gkitkplot.py
pyraf/graphcap.py
pyraf/gwm.py
pyraf/ipython_api.py
pyraf/ipythonrc-pyraf
pyraf/iraf.py
pyraf/irafcompleter.py
pyraf/irafdisplay.py
pyraf/irafecl.py
pyraf/irafexecute.py
pyraf/iraffunctions.py
pyraf/irafgwcs.py
pyraf/irafhelp.py
pyraf/irafimcur.py
pyraf/irafimport.py
pyraf/irafinst.py
pyraf/irafnames.py
pyraf/irafpar.py
pyraf/iraftask.py
pyraf/irafukey.py
pyraf/msgiobuffer.py
pyraf/msgiowidget.py
pyraf/newWindowHack.py
pyraf/pseteparoption.py
pyraf/pycmdline.py
pyraf/pyrafTk.py
pyraf/pyrafglobals.py
pyraf/pyraflogo_rgb_web.gif
pyraf/scanf.py
pyraf/splash.py
pyraf/sqliteshelve.py
pyraf/subproc.py
pyraf/textattrib.py
pyraf/tkplottext.py
pyraf/tpar.py
pyraf/urwfiledlg.py
pyraf/urwutil.py
pyraf/version.py
pyraf/wutil.py
pyraf/xutil.c
pyraf.egg-info/PKG-INFO
pyraf.egg-info/SOURCES.txt
pyraf.egg-info/dependency_links.txt
pyraf.egg-info/entry_points.txt
pyraf.egg-info/requires.txt
pyraf.egg-info/top_level.txt
pyraf/noiraf/cl.par
pyraf/noiraf/clpackage.cl
pyraf/noiraf/login.cl
pyraf/noiraf/system.cl
pyraf/noiraf/system.par
pyraf/tests/__init__.py
pyraf/tests/test_basic.py
pyraf/tests/test_clcache.py
pyraf/tests/test_cli.py
pyraf/tests/test_core_nongraphics.py
pyraf/tests/test_graphics.py
pyraf/tests/test_invocation.py
pyraf/tests/test_plot.py
pyraf/tests/test_tasks.py
pyraf/tests/test_using_tasks.py
pyraf/tests/utils.py
