Metadata-Version: 2.4
Name: pyraf
Version: 2.2.3
Summary: Pythonic interface to IRAF that can be used in place of the existing IRAF CL
Author: Rick White, Perry Greenfield, Chris Sontag, Ole Streicher
License: BSD 3-Clause
Keywords: astronomy,astrophysics,utility,iraf
Classifier: Intended Audience :: Science/Research
Classifier: License :: OSI Approved :: BSD License
Classifier: Operating System :: OS Independent
Classifier: Programming Language :: Python :: 3
Classifier: Topic :: Scientific/Engineering :: Astronomy
Requires-Python: >=3.6
License-File: LICENSE.txt
Requires-Dist: configobj
Requires-Dist: numpy
Requires-Dist: pyobjc; sys_platform == "darwin"
Provides-Extra: docs
Requires-Dist: astropy-sphinx-theme; extra == "docs"
Requires-Dist: numpydoc; extra == "docs"
Requires-Dist: sphinx; extra == "docs"
Provides-Extra: test
Requires-Dist: astropy; extra == "test"
Requires-Dist: pytest; extra == "test"
Dynamic: license-file
